libname/__init__.py
libname/hello.py
libname/models/opencv-4.10.0.zip
adeopencv-4.10.0.dist-info/METADATA
adeopencv-4.10.0.dist-info/WHEEL
adeopencv-4.10.0.dist-info/top_level.txt
adeopencv-4.10.0.dist-info/RECORD
